upparat/__init__.py
upparat/cli.py
upparat/config.py
upparat/events.py
upparat/hooks.py
upparat/jobs.py
upparat/mqtt.py
upparat/statemachine/__init__.py
upparat/statemachine/download.py
upparat/statemachine/fetch_jobs.py
upparat/statemachine/install.py
upparat/statemachine/machine.py
upparat/statemachine/monitor.py
upparat/statemachine/restart.py
upparat/statemachine/select_job.py
upparat/statemachine/verify_installation.py
upparat/statemachine/verify_job.py
upparat-1.12.dist-info/LICENSE.txt
upparat-1.12.dist-info/METADATA
upparat-1.12.dist-info/WHEEL
upparat-1.12.dist-info/entry_points.txt
upparat-1.12.dist-info/top_level.txt
upparat-1.12.dist-info/RECORD
