Metadata-Version: 2.1
Name: upparat
Version: 1.12
Summary: Update Service for AWS IoT Core
Home-page: https://github.com/caruhome/upparat
Author: Livio Bieri / Reto Aebersold
License: MIT
Platform: UNKNOWN
Classifier: Development Status :: 5 - Production/Stable
Classifier: Intended Audience :: System Administrators
Classifier: Intended Audience :: Developers
Classifier: License :: OSI Approved :: MIT License
Classifier: Operating System :: POSIX
Classifier: Programming Language :: Python :: 3
Classifier: Topic :: System :: Installation/Setup
Classifier: Topic :: System :: Operating System
Requires-Python: >=3.6
Requires-Dist: paho-mqtt (>=1.4.0)
Requires-Dist: backoff (>=1.8.1)
Requires-Dist: pysm (>=0.3.7)
Provides-Extra: dev
Requires-Dist: pytest ; extra == 'dev'
Requires-Dist: pytest-mock ; extra == 'dev'
Requires-Dist: boto3 ; extra == 'dev'
Requires-Dist: ipdb ; extra == 'dev'
Requires-Dist: coverage ; extra == 'dev'
Provides-Extra: sentry
Requires-Dist: sentry-sdk ; extra == 'sentry'
